verilog/tw_multiplexer/tw_multiplexer.sv
///////////////////////////////////////////////////////////////////////////////
//
// two way multiplexer module
//
// An two way multiplexer module for your Computer Architecture Elements Catalog
//
// module: two way multiplexer
// hdl: Verilog
//
// author: Lei(Raymond) Chi <lei.chi@cooper.edu>
//
///////////////////////////////////////////////////////////////////////////////
`timescale 1ns/1ps

module tw_multiplexer (
    input logic in1, in2, ctrl,
    output logic out
);

    assign out = (ctrl & in2) | (!ctrl & in1);

endmodule

verilog/tw_multiplexer/tw_multiplexer_tb.sv
///////////////////////////////////////////////////////////////////////////////
//
// two way multiplexer TESTBENCH module
//
// An two way multiplexer testbench module for your Computer Architecture Elements Catalog
//
// module: two way multiplexer
// hdl: Verilog
//
// author: Lei(Raymond) Chi <lei.chi@cooper.edu>
//
///////////////////////////////////////////////////////////////////////////////
`timescale 1ns/1ps

module tw_multiplexer_tb;

    logic in1, in2, ctrl, out;
    

    tw_multiplexer DUT (.in1(in1), .in2(in2), .ctrl(ctrl), .out(out));

    initial begin
        $monitor("in1 = %b, in2 = %b, ctrl = %b, out = %b", in1, in2, ctrl,  out);
    end
    
    initial begin
        in1 = 1'b0;
        in2 = 1'b0;
        ctrl = 1'b0;

        #10
        in1 = 1'b0;
        in2 = 1'b0;
        ctrl = 1'b1;

        #10
        in1 = 1'b0;
        in2 = 1'b1;
        ctrl = 1'b0;

        #10
        in1 = 1'b0;
        in2 = 1'b1;
        ctrl = 1'b1;

        #10
        in1 = 1'b1;
        in2 = 1'b0;
        ctrl = 1'b0;

        #10
        in1 = 1'b1;
        in2 = 1'b0;
        ctrl = 1'b1;

        #10
        in1 = 1'b1;
        in2 = 1'b1;
        ctrl = 1'b0;

        #10
        in1 = 1'b1;
        in2 = 1'b1;
        ctrl = 1'b1;

        #10 
        $finish;
    end

    initial begin
        $dumpfile("waveForm.vcd");
        $dumpvars(0, DUT);
    end

endmodule

verilog/tw_multiplexer/waveForm.vcd
$date
	Sun Mar 12 18:37:31 2023
$end
$version
	Icarus Verilog
$end
$timescale
	1ps
$end
$scope module tw_multiplexer_tb $end
$scope module DUT $end
$var wire 1 ! ctrl $end
$var wire 1 " in1 $end
$var wire 1 # in2 $end
$var wire 1 $ out $end
$upscope $end
$upscope $end
$enddefinitions $end
#0
$dumpvars
0$
0#
0"
0!
$end
#10000
1!
#20000
0!
1#
#30000
1$
1!
#40000
0!
0#
1"
#50000
0$
1!
#60000
1$
0!
1#
#70000
1!
