verilog/fw_multiplexer/fw_multiplexer.sv
///////////////////////////////////////////////////////////////////////////////
//
// four way multiplexer module
//
// An four way multiplexer module for your Computer Architecture Elements Catalog
//
// module: four way multiplexer
// hdl: Verilog
//
// author: Lei(Raymond) <lei.chi@cooper.edu>
//
///////////////////////////////////////////////////////////////////////////////
module mux4(input [3:0] data_in, input [1:0] select, output reg out);

always @(*)
begin
    case(select)
        2'b00: out = data_in[0];
        2'b01: out = data_in[1];
        2'b10: out = data_in[2];
        2'b11: out = data_in[3];
    endcase
end

endmodule

verilog/fw_multiplexer/fw_multiplexer_tb.sv
///////////////////////////////////////////////////////////////////////////////
//
// four way multiplexer TESTBENCH module
//
// An four way multiplexer testbench module for your Computer Architecture Elements Catalog
//
// module: four way multiplexer
// hdl: Verilog
//
// author: Lei(Raymond) Chi <lei.chi@cooper.edu>
//
///////////////////////////////////////////////////////////////////////////////

`timescale 1ns/1ps

module mux4_tb;

   
    logic [3:0] data_in;
    logic [1:0] select;
    logic out;

   
    mux4 DUT (.data_in(data_in), .select(select), .out(out));

    
    initial begin
        data_in = 4'b0000;
        select = 2'b00;
        #10;
        
        data_in = 4'b0001;
        select = 2'b00;
        #10;
        
        data_in = 4'b0010;
        select = 2'b00;
        #10;
        
        data_in = 4'b0100;
        select = 2'b00;
        #10;
        
        data_in = 4'b0000;
        select = 2'b01;
        #10;
        
        data_in = 4'b0001;
        select = 2'b01;
        #10;
        
        data_in = 4'b0010;
        select = 2'b01;
        #10;
        
        data_in = 4'b0100;
        select = 2'b01;
        #10;
        
        data_in = 4'b0000;
        select = 2'b10;
        #10;
        
        data_in = 4'b0001;
        select = 2'b10;
        #10;
        
        data_in = 4'b0010;
        select = 2'b10;
        #10;
        
        data_in = 4'b0100;
        select = 2'b10;
        #10;
        
        data_in = 4'b0000;
        select = 2'b11;
        #10;
        
        data_in = 4'b0001;
        select = 2'b11;
        #10;
        
        data_in = 4'b0010;
        select = 2'b11;
        #10;
        
        data_in = 4'b0100;
        select = 2'b11;
        #10;
        
        $finish;
    end

    
    initial begin
        $dumpfile("mux4.vcd");
        $dumpvars(0, DUT);
    end

endmodule

verilog/fw_multiplexer/mux4.vcd
$date
	Sun Mar 12 19:28:52 2023
$end
$version
	Icarus Verilog
$end
$timescale
	1ps
$end
$scope module mux4_tb $end
$scope module DUT $end
$var wire 4 ! data_in [3:0] $end
$var wire 2 " select [1:0] $end
$var reg 1 # out $end
$upscope $end
$upscope $end
$enddefinitions $end
#0
$dumpvars
0#
b0 "
b0 !
$end
#10000
1#
b1 !
#20000
0#
b10 !
#30000
b100 !
#40000
b1 "
b0 !
#50000
b1 !
#60000
1#
b10 !
#70000
0#
b100 !
#80000
b10 "
b0 !
#90000
b1 !
#100000
b10 !
#110000
1#
b100 !
#120000
0#
b11 "
b0 !
#130000
b1 !
#140000
b10 !
#150000
b100 !
